setup.py
emailvision/__init__.py
emailvision/api.py
python_emailvision.egg-info/PKG-INFO
python_emailvision.egg-info/SOURCES.txt
python_emailvision.egg-info/dependency_links.txt
python_emailvision.egg-info/requires.txt
python_emailvision.egg-info/top_level.txt
python_emailvision.egg-info/zip-safe