Metadata-Version: 1.1
Name: python-emailvision
Version: 1.0
Summary: EmailVision API wrapper for Python.
Home-page: https://github.com/eugene-wee/python-emailvision
Author: Eugene Wee
Author-email: UNKNOWN
License: UNKNOWN
Download-URL: https://github.com/eugene-wee/python-emailvision/tarball/master
Keywords: emailvision api wrapper
Platform: UNKNOWN
Classifier: Development Status :: 5 - Production/Stable
Classifier: Intended Audience :: Developers
Classifier: License :: OSI Approved :: Apache Software License
Classifier: Natural Language :: English
Classifier: Operating System :: OS Independent
Classifier: Programming Language :: Python
Classifier: Topic :: Software Development :: Libraries :: Python Modules
